pylol/__init__.py
pylol/agents/__init__.py
pylol/agents/base_agent.py
pylol/agents/random_agent.py
pylol/agents/scripted_agent.py
pylol/bin/__init__.py
pylol/bin/client.py
pylol/bin/map_list.py
pylol/bin/parallel.py
pylol/bin/valid_actions.py
pylol/env/__init__.py
pylol/env/available_actions_printer.py
pylol/env/base_env_wrapper.py
pylol/env/environment.py
pylol/env/lol_env.py
pylol/env/run_loop.py
pylol/lib/__init__.py
pylol/lib/actions.py
pylol/lib/common.py
pylol/lib/features.py
pylol/lib/lol_process.py
pylol/lib/named_array.py
pylol/lib/point.py
pylol/lib/point_flag.py
pylol/lib/portspicker.py
pylol/lib/protocol.py
pylol/lib/remote_controller.py
pylol/lib/run_parallel.py
pylol/lib/utils.py
pylol/maps/__init__.py
pylol/maps/howling_abyss.py
pylol/maps/lib.py
pylol/maps/new_summoners_rift.py
pylol/maps/old_summoners_rift.py
pylol/run_configs/__init__.py
pylol/run_configs/lib.py
pylol/run_configs/platforms.py
pylol/tests/__init__.py
pylol/tests/random_agent_test.py
pylol/tests/utils.py
pylol_rl-1.0.0.dist-info/LICENSE
pylol_rl-1.0.0.dist-info/METADATA
pylol_rl-1.0.0.dist-info/WHEEL
pylol_rl-1.0.0.dist-info/top_level.txt
pylol_rl-1.0.0.dist-info/RECORD
